diagram_renderer/__init__.py
diagram_renderer/__version__.py
diagram_renderer/cli.py
diagram_renderer/error_pages.py
diagram_renderer/external_diagrams.py
diagram_renderer/mermaid_config.py
diagram_renderer/py.typed
diagram_renderer/resource_cache.py
diagram_renderer/template_engine.py
diagram_renderer/renderers/__init__.py
diagram_renderer/renderers/base.py
diagram_renderer/renderers/graphviz.py
diagram_renderer/renderers/mermaid.py
diagram_renderer/renderers/plantuml.py
diagram_renderer/renderers/static/js/README-plugins.txt
diagram_renderer/renderers/static/js/mermaid.min.js
diagram_renderer/renderers/static/js/panzoom.min.js
diagram_renderer/renderers/static/js/viz-full.js
diagram_renderer/renderers/static/js/viz-lite.js
diagram_renderer/renderers/templates/unified.html
diagram_renderer-2025.9.24.103.dist-info/licenses/LICENSE
diagram_renderer-2025.9.24.103.dist-info/METADATA
diagram_renderer-2025.9.24.103.dist-info/WHEEL
diagram_renderer-2025.9.24.103.dist-info/entry_points.txt
diagram_renderer-2025.9.24.103.dist-info/top_level.txt
diagram_renderer-2025.9.24.103.dist-info/RECORD
