Metadata-Version: 2.4
Name: diagram-renderer
Version: 2025.9.24.103
Summary: A comprehensive diagram rendering service supporting Mermaid, PlantUML, and Graphviz diagrams with interactive zoom/pan controls and PNG export
Author-email: Danny Volz <volz.developer+diagram-renderer@gmail.com>
Maintainer-email: Danny Volz <volz.developer+diagram-renderer@gmail.com>
License-Expression: MIT
Project-URL: Homepage, https://github.com/djvolz/diagram-renderer
Project-URL: Documentation, https://github.com/djvolz/diagram-renderer#readme
Project-URL: Repository, https://github.com/djvolz/diagram-renderer.git
Project-URL: Bug Tracker, https://github.com/djvolz/diagram-renderer/issues
Project-URL: Changelog, https://github.com/djvolz/diagram-renderer/blob/main/CHANGELOG.md
Keywords: diagram,mermaid,plantuml,graphviz,visualization,renderer
Classifier: Development Status :: 4 - Beta
Classifier: Intended Audience :: Developers
Classifier: Operating System :: OS Independent
Classifier: Programming Language :: Python :: 3
Classifier: Programming Language :: Python :: 3.10
Classifier: Programming Language :: Python :: 3.11
Classifier: Programming Language :: Python :: 3.12
Classifier: Programming Language :: Python :: 3.13
Classifier: Topic :: Software Development :: Libraries :: Python Modules
Classifier: Topic :: Scientific/Engineering :: Visualization
Classifier: Topic :: Text Processing :: Markup
Requires-Python: >=3.10
License-File: LICENSE
Provides-Extra: cli
Requires-Dist: click>=8.0.0; extra == "cli"
Provides-Extra: dashboard
Requires-Dist: streamlit>=1.46.1; extra == "dashboard"
Provides-Extra: webapp
Requires-Dist: fastapi>=0.104.0; extra == "webapp"
Requires-Dist: uvicorn[standard]>=0.24.0; extra == "webapp"
Requires-Dist: pydantic>=2.5.0; extra == "webapp"
Requires-Dist: httpx>=0.25.0; extra == "webapp"
Provides-Extra: mcp
Requires-Dist: mcp>=1.0.0; extra == "mcp"
Provides-Extra: dev
Requires-Dist: pytest>=8.4.1; extra == "dev"
Requires-Dist: pytest-cov>=4.0.0; extra == "dev"
Requires-Dist: ruff>=0.1.0; extra == "dev"
Requires-Dist: mypy>=1.5.0; extra == "dev"
Requires-Dist: pillow>=10.0.0; extra == "dev"
Requires-Dist: numpy>=1.24.0; extra == "dev"
Requires-Dist: playwright>=1.40.0; extra == "dev"
Provides-Extra: all
Requires-Dist: click>=8.0.0; extra == "all"
Requires-Dist: streamlit>=1.46.1; extra == "all"
Requires-Dist: fastapi>=0.104.0; extra == "all"
Requires-Dist: uvicorn[standard]>=0.24.0; extra == "all"
Requires-Dist: pydantic>=2.5.0; extra == "all"
Requires-Dist: mcp>=1.0.0; extra == "all"
Requires-Dist: pytest>=8.4.1; extra == "all"
Requires-Dist: pytest-cov>=4.0.0; extra == "all"
Requires-Dist: ruff>=0.1.0; extra == "all"
Requires-Dist: mypy>=1.5.0; extra == "all"
Dynamic: license-file
